pybackend_libs/__init__.py
pybackend_libs/dataelem/__init__.py
pybackend_libs/dataelem/framework/__init__.py
pybackend_libs/dataelem/framework/hf_model.py
pybackend_libs/dataelem/framework/onnx_graph.py
pybackend_libs/dataelem/framework/pt_graph.py
pybackend_libs/dataelem/framework/tf_graph.py
pybackend_libs/dataelem/model/__init__.py
pybackend_libs/dataelem/model/embedding/__init__.py
pybackend_libs/dataelem/model/embedding/bge.py
pybackend_libs/dataelem/model/embedding/embedding.py
pybackend_libs/dataelem/model/embedding/gte.py
pybackend_libs/dataelem/model/embedding/me5.py
pybackend_libs/dataelem/model/embedding/rocketqa_dual.py
pybackend_libs/dataelem/model/layout/__init__.py
pybackend_libs/dataelem/model/layout/config.py
pybackend_libs/dataelem/model/layout/layout_mrcnn.py
pybackend_libs/dataelem/model/layout/mrcnn_pt.py
pybackend_libs/dataelem/model/llama_cpp/__init__.py
pybackend_libs/dataelem/model/llama_cpp/lc_model.py
pybackend_libs/dataelem/model/llm/__init__.py
pybackend_libs/dataelem/model/llm/baichuan.py
pybackend_libs/dataelem/model/llm/chatglm2.py
pybackend_libs/dataelem/model/llm/chatglm2_utils.py
pybackend_libs/dataelem/model/llm/chatglm3.py
pybackend_libs/dataelem/model/llm/code_geex2.py
pybackend_libs/dataelem/model/llm/internlm.py
pybackend_libs/dataelem/model/llm/llama2.py
pybackend_libs/dataelem/model/llm/llama2_utils.py
pybackend_libs/dataelem/model/llm/llm.py
pybackend_libs/dataelem/model/llm/qwen.py
pybackend_libs/dataelem/model/llm/qwen_utils.py
pybackend_libs/dataelem/model/llm/vicuna.py
pybackend_libs/dataelem/model/llm/xverse.py
pybackend_libs/dataelem/model/llm/yi.py
pybackend_libs/dataelem/model/llm/yuan.py
pybackend_libs/dataelem/model/mmu/__init__.py
pybackend_libs/dataelem/model/mmu/visualglm.py
pybackend_libs/dataelem/model/ocr/__init__.py
pybackend_libs/dataelem/model/ocr/latex_det.py
pybackend_libs/dataelem/model/ocr/latex_recog.py
pybackend_libs/dataelem/model/ocr/ocr_client.py
pybackend_libs/dataelem/model/table/__init__.py
bisheng_pybackend_libs-0.0.6.4.dist-info/METADATA
bisheng_pybackend_libs-0.0.6.4.dist-info/WHEEL
bisheng_pybackend_libs-0.0.6.4.dist-info/top_level.txt
bisheng_pybackend_libs-0.0.6.4.dist-info/RECORD
